systemrdl/__about__.py
systemrdl/__init__.py
systemrdl/compiler.py
systemrdl/component.py
systemrdl/importer.py
systemrdl/messages.py
systemrdl/node.py
systemrdl/py.typed
systemrdl/source_ref.py
systemrdl/udp.py
systemrdl/walker.py
systemrdl/warnings.py
systemrdl/ast/__init__.py
systemrdl/ast/ast_node.py
systemrdl/ast/binary.py
systemrdl/ast/boolean.py
systemrdl/ast/cast.py
systemrdl/ast/conditional.py
systemrdl/ast/exponential.py
systemrdl/ast/literals.py
systemrdl/ast/reduction.py
systemrdl/ast/references.py
systemrdl/ast/relational.py
systemrdl/ast/sequence.py
systemrdl/ast/unary.py
systemrdl/core/BaseVisitor.py
systemrdl/core/ComponentVisitor.py
systemrdl/core/EnumVisitor.py
systemrdl/core/ExprVisitor.py
systemrdl/core/StructVisitor.py
systemrdl/core/UDPVisitor.py
systemrdl/core/__init__.py
systemrdl/core/elaborate.py
systemrdl/core/helpers.py
systemrdl/core/namespace.py
systemrdl/core/parameter.py
systemrdl/core/rdlformatcode.py
systemrdl/core/validate.py
systemrdl/core/value_normalization.py
systemrdl/parser/SystemRDL.g4
systemrdl/parser/SystemRDL.interp
systemrdl/parser/SystemRDL.tokens
systemrdl/parser/SystemRDLLexer.interp
systemrdl/parser/SystemRDLLexer.py
systemrdl/parser/SystemRDLLexer.tokens
systemrdl/parser/SystemRDLParser.py
systemrdl/parser/SystemRDLParser.pyi
systemrdl/parser/SystemRDLVisitor.py
systemrdl/parser/__init__.py
systemrdl/parser/generate_parser.sh
systemrdl/parser/sa_systemrdl.py
systemrdl/parser/sa_systemrdl_cpp_parser.abi3.so
systemrdl/parser/ext/SystemRDL.interp
systemrdl/parser/ext/SystemRDL.tokens
systemrdl/parser/ext/SystemRDLBaseVisitor.cpp
systemrdl/parser/ext/SystemRDLBaseVisitor.h
systemrdl/parser/ext/SystemRDLLexer.cpp
systemrdl/parser/ext/SystemRDLLexer.h
systemrdl/parser/ext/SystemRDLLexer.interp
systemrdl/parser/ext/SystemRDLLexer.tokens
systemrdl/parser/ext/SystemRDLParser.cpp
systemrdl/parser/ext/SystemRDLParser.h
systemrdl/parser/ext/SystemRDLVisitor.cpp
systemrdl_compiler-1.31.0.dist-info/LICENSE
systemrdl_compiler-1.31.0.dist-info/LICENSE-3RD-PARTY
systemrdl_compiler-1.31.0.dist-info/METADATA
systemrdl_compiler-1.31.0.dist-info/WHEEL
systemrdl_compiler-1.31.0.dist-info/top_level.txt
systemrdl_compiler-1.31.0.dist-info/RECORD
