Metadata-Version: 2.4
Name: systemrdl-compiler
Version: 1.31.0
Summary: Parse and elaborate front-end for SystemRDL 2.0
Author: Alex Mykyta
License: MIT
Project-URL: Source, https://github.com/SystemRDL/systemrdl-compiler
Project-URL: Tracker, https://github.com/SystemRDL/systemrdl-compiler/issues
Project-URL: Changelog, https://github.com/SystemRDL/systemrdl-compiler/releases
Project-URL: Documentation, http://systemrdl-compiler.readthedocs.io
Keywords: SystemRDL,CSR,compiler,tool,registers,generator,register abstraction layer,FPGA,ASIC
Classifier: Development Status :: 5 - Production/Stable
Classifier: Programming Language :: Python
Classifier: Programming Language :: Python :: 3
Classifier: Programming Language :: Python :: 3 :: Only
Classifier: Intended Audience :: Developers
Classifier: License :: OSI Approved :: MIT License
Classifier: Operating System :: OS Independent
Classifier: Topic :: Scientific/Engineering :: Electronic Design Automation (EDA)
Classifier: Topic :: Software Development :: Compilers
Classifier: Topic :: Software Development :: Code Generators
Requires-Python: >=3.7
License-File: LICENSE
License-File: LICENSE-3RD-PARTY
Requires-Dist: antlr4-python3-runtime<4.14,>=4.11
Requires-Dist: colorama
Requires-Dist: markdown
Requires-Dist: typing_extensions
Dynamic: license-file
